savings.py
savings-0.0.1.dist-info/WHEEL
savings-0.0.1.dist-info/METADATA
savings-0.0.1.dist-info/RECORD
