Metadata-Version: 2.1
Name: savings
Version: 0.0.1
Summary: Module documentation here...
Author-email: OV <olav.vahtras@gmail.com>
